AUTHORS.rst
CHANGELOG.rst
LICENSE
MANIFEST.in
README.rst
setup.py
django_object_tools.egg-info/PKG-INFO
django_object_tools.egg-info/SOURCES.txt
django_object_tools.egg-info/dependency_links.txt
django_object_tools.egg-info/not-zip-safe
django_object_tools.egg-info/top_level.txt
object_tools/__init__.py
object_tools/apps.py
object_tools/models.py
object_tools/options.py
object_tools/sites.py
object_tools/validation.py
object_tools/management/__init__.py
object_tools/management/__init__.pyc
object_tools/management/__pycache__/__init__.cpython-36.pyc
object_tools/management/__pycache__/__init__.cpython-37.pyc
object_tools/templates/admin/change_list.html
object_tools/templates/object_tools/tool_base.html
object_tools/templates/object_tools/inclusion_tags/object_tools.html
object_tools/templatetags/__init__.py
object_tools/templatetags/__init__.pyc
object_tools/templatetags/object_tools_compat.py
object_tools/templatetags/object_tools_compat.pyc
object_tools/templatetags/object_tools_inclusion_tags.py
object_tools/templatetags/object_tools_inclusion_tags.pyc
object_tools/templatetags/__pycache__/__init__.cpython-36.pyc
object_tools/templatetags/__pycache__/__init__.cpython-37.pyc
object_tools/templatetags/__pycache__/object_tools_compat.cpython-36.pyc
object_tools/templatetags/__pycache__/object_tools_compat.cpython-37.pyc
object_tools/templatetags/__pycache__/object_tools_inclusion_tags.cpython-36.pyc
object_tools/templatetags/__pycache__/object_tools_inclusion_tags.cpython-37.pyc
object_tools/tests/__init__.py
object_tools/tests/__init__.pyc
object_tools/tests/test_changelist_views.py
object_tools/tests/test_changelist_views.pyc
object_tools/tests/test_inclusion_tag.py
object_tools/tests/test_inclusion_tag.pyc
object_tools/tests/test_object_tool_creation.py
object_tools/tests/test_object_tool_creation.pyc
object_tools/tests/test_object_tools_config.py
object_tools/tests/test_object_tools_config.pyc
object_tools/tests/tools.py
object_tools/tests/tools.pyc
object_tools/tests/urls.py
object_tools/tests/urls.pyc
object_tools/tests/__pycache__/__init__.cpython-36.pyc
object_tools/tests/__pycache__/__init__.cpython-37.pyc
